latex_flatten/__init__.py
latex_flatten/__main__.py
latex_flatten-0.3.0.dist-info/LICENSES/GPL-3.0-or-later.txt
latex_flatten-0.3.0.dist-info/METADATA
latex_flatten-0.3.0.dist-info/WHEEL
latex_flatten-0.3.0.dist-info/entry_points.txt
latex_flatten-0.3.0.dist-info/RECORD
