Metadata-Version: 2.1
Name: latex-flatten
Version: 0.3.0
Summary: Flatten your LaTeX document
License: GPL3
Author: Yann Büchau
Author-email: nobodyinperson@posteo.de
Requires-Python: >=3.11,<4.0
Classifier: License :: Other/Proprietary License
Classifier: Programming Language :: Python :: 3
Classifier: Programming Language :: Python :: 3.11
Classifier: Programming Language :: Python :: 3.12
Requires-Dist: rich (>=13.7.0,<14.0.0)
